{"city": {"昆明市": 23}, "province": {"云南": 32}, "industry": {"L1-医药生物": 217, "L2-中药": 59, "L3-中药": 59}, "concept": {"标普道琼斯A股": 1097, "深股通": 597, "融资融券": 1395, "健康中国": 66, "工业大麻": 39, "沪深300样本股": 270, "MSCI概念": 468, "同花顺漂亮100": 76, "超级品牌": 24, "参股券商": 115, "口罩": 100}, "investor": {"中国证券金融股份有限公司": 451, "中央汇金资产管理有限责任公司": 822, "香港中央结算有限公司(陆股通)": 1049, "云南合和(集团)股份有限公司": 9, "香港金融管理局-自有资金": 16, "全国社保基金四一四组合": 32, "江苏鱼跃科技发展有限公司": 3, "全国社保基金一一二组合": 24, "全国社保基金一零八组合": 43, "云南白药控股有限公司": 1, "陈发树": 4, "新华都实业集团股份有限公司": 2, "中国平安人寿保险股份有限公司-自有资金": 2}, "management": {"尹晓冰": 6, "汪戎": 1, "纳鹏杰": 7, "龙江": 1, "李双友": 5, "杨发甲": 3, "刘会疆": 3, "杨益清": 1, "潘以文": 1, "王明辉": 2, "王雷": 2, "黄艾农": 1, "任德权": 3, "项兵": 6, "郝小江": 1, "林瑞超": 1, "吴群": 3, "赵勇": 1, "王方华": 13, "宋成立": 2, "王化成": 9, "王建华": 2, "邱晓华": 4, "曲晓辉": 4, "陈小悦": 8, "张萌": 1, "吴伟": 1, "刘劲": 2, "谭跃": 1, "徐飞": 3, "戴扬": 2}}